{
  "parent": "minecraft:recipes/root",
  "criteria": {
    "has_dried_peat_clump": {
      "conditions": {
        "items": [
          {
            "items": "wilderworld:dried_peat_clump"
          }
        ]
      },
      "trigger": "minecraft:inventory_changed"
    },
    "has_plant_fiber": {
      "conditions": {
        "items": [
          {
            "items": "wilderworld:plant_fiber"
          }
        ]
      },
      "trigger": "minecraft:inventory_changed"
    },
    "has_the_recipe": {
      "conditions": {
        "recipe": "wilderworld:dried_peat_block_recipe"
      },
      "trigger": "minecraft:recipe_unlocked"
    }
  },
  "requirements": [
    [
      "has_the_recipe",
      "has_dried_peat_clump",
      "has_plant_fiber"
    ]
  ],
  "rewards": {
    "recipes": [
      "wilderworld:dried_peat_block_recipe"
    ]
  }
}